mps_motion/__init__.py
mps_motion/__main__.py
mps_motion/block_matching.py
mps_motion/cli.py
mps_motion/dualtvl1.py
mps_motion/farneback.py
mps_motion/filters.py
mps_motion/frame_sequence.py
mps_motion/gui.py
mps_motion/lucas_kanade.py
mps_motion/mechanics.py
mps_motion/motion_tracking.py
mps_motion/scaling.py
mps_motion/stats.py
mps_motion/utils.py
mps_motion/visu.py
mps_motion-0.5.0.dist-info/LICENSE
mps_motion-0.5.0.dist-info/METADATA
mps_motion-0.5.0.dist-info/WHEEL
mps_motion-0.5.0.dist-info/entry_points.txt
mps_motion-0.5.0.dist-info/top_level.txt
mps_motion-0.5.0.dist-info/RECORD
