Metadata-Version: 2.2
Name: mps_motion
Version: 0.5.0
Summary: Library for tracking motion in cardiac mps data
Author-email: Henrik Finsberg <henriknf@simula.no>
License: MIT
Project-URL: Homepage, https://github.com/ComputationalPhysiology/mps_motion
Keywords: motion tracking,computer vision,optical flow,cardiac
Classifier: License :: OSI Approved :: MIT License
Classifier: Programming Language :: Python :: 3
Classifier: Programming Language :: Python :: 3 :: Only
Requires-Python: >=3.8
License-File: LICENSE
Requires-Dist: ap-features
Requires-Dist: cardiac-mps
Requires-Dist: daiquiri
Requires-Dist: dask-image
Requires-Dist: dask[array,diagnostics]
Requires-Dist: h5py
Requires-Dist: matplotlib
Requires-Dist: numba
Requires-Dist: numpy
Requires-Dist: opencv-contrib-python
Requires-Dist: opencv-python
Requires-Dist: scipy
Requires-Dist: tqdm
Requires-Dist: typer
Requires-Dist: typing-extensions
Provides-Extra: benchmark
Requires-Dist: flowiz; extra == "benchmark"
Provides-Extra: dev
Requires-Dist: bump-my-version; extra == "dev"
Requires-Dist: ipython; extra == "dev"
Requires-Dist: pdbpp; extra == "dev"
Requires-Dist: pre-commit; extra == "dev"
Provides-Extra: docs
Requires-Dist: jupyter-book; extra == "docs"
Provides-Extra: gui
Requires-Dist: streamlit; extra == "gui"
Provides-Extra: pypi
Requires-Dist: build; extra == "pypi"
Provides-Extra: test
Requires-Dist: pytest; extra == "test"
Requires-Dist: pytest-cov; extra == "test"
